MANIFEST.in
setup.py
Hook/__init__.py
Hook/exceptions.py
Hook/ext.py
Hook/models.py
Hook/data/static/css/bootstrap-switch.min.css
Hook/data/static/css/fa-social.css
Hook/data/static/css/style.css
Hook/data/static/favicon/android-icon-144x144.png
Hook/data/static/favicon/android-icon-192x192.png
Hook/data/static/favicon/android-icon-36x36.png
Hook/data/static/favicon/android-icon-48x48.png
Hook/data/static/favicon/android-icon-72x72.png
Hook/data/static/favicon/android-icon-96x96.png
Hook/data/static/favicon/apple-icon-114x114.png
Hook/data/static/favicon/apple-icon-120x120.png
Hook/data/static/favicon/apple-icon-144x144.png
Hook/data/static/favicon/apple-icon-152x152.png
Hook/data/static/favicon/apple-icon-180x180.png
Hook/data/static/favicon/apple-icon-57x57.png
Hook/data/static/favicon/apple-icon-60x60.png
Hook/data/static/favicon/apple-icon-72x72.png
Hook/data/static/favicon/apple-icon-76x76.png
Hook/data/static/favicon/apple-icon-precomposed.png
Hook/data/static/favicon/apple-icon.png
Hook/data/static/favicon/browserconfig.xml
Hook/data/static/favicon/favicon-16x16.png
Hook/data/static/favicon/favicon-32x32.png
Hook/data/static/favicon/favicon-96x96.png
Hook/data/static/favicon/favicon.ico
Hook/data/static/favicon/manifest.json
Hook/data/static/favicon/ms-icon-144x144.png
Hook/data/static/favicon/ms-icon-150x150.png
Hook/data/static/favicon/ms-icon-310x310.png
Hook/data/static/favicon/ms-icon-70x70.png
Hook/data/static/images/GitHub-Mark.png
Hook/data/static/js/bootstrap-switch.min.js
Hook/data/static/js/format.log.js
Hook/data/templates/container-2col.html
Hook/data/templates/container.html
Hook/data/templates/header.html
Hook/data/templates/index.html
Hook/data/templates/login.html
Hook/data/templates/menu.html
Hook/data/templates/repo.html
Hook/data/templates/report.html
Hook/data/templates/svg/build.coverage.acceptable.xml
Hook/data/templates/svg/build.coverage.failure.xml
Hook/data/templates/svg/build.coverage.success.xml
capitains_hook.egg-info/PKG-INFO
capitains_hook.egg-info/SOURCES.txt
capitains_hook.egg-info/dependency_links.txt
capitains_hook.egg-info/not-zip-safe
capitains_hook.egg-info/requires.txt
capitains_hook.egg-info/top_level.txt
