Metadata-Version: 1.0
Name: capitains-hook
Version: 1.0.0
Summary: Hook Flask App for Github/CTS repositories
Home-page: http://github.com/Capitains/Hook
Author: Thibault Clerice
Author-email: leponteineptique@gmail.com
License: GNU GPL
Platform: UNKNOWN
